{"_response_info":{"status":"ok"},"id":"https://www.gov.uk/api/self-assessment-tax-return-deadlines.json","web_url":"https://www.gov.uk/self-assessment-tax-return-deadlines","title":"Self Assessment deadlines 2011 to 2012 tax year","format":"answer","updated_at":"2012-10-31T14:16:55+00:00","details":{"need_id":"B100","business_proposition":true,"description":"Self Assessment tax return deadlines - deadlines for your tax return and paying your tax ","language":"en","body":"\n<div class=\"summary\">\n<p>There are deadlines for sending your Self Assessment tax return to HM Revenue &amp; Customs and paying any tax you owe.</p>\n</div>\n\n<p>For the 2011 to 2012 tax year (which ended 5 April 2012) your main deadlines are:</p>\n\n<ul>\n  <li>paper tax returns - by midnight 31 October 2012</li>\n  <li>online tax returns - by midnight 31 January 2013</li>\n  <li>final payment of any tax due - by midnight 31 January 2013</li>\n</ul>\n\n<p>There are <a href=\"/self-assessment-tax-returns/deadlines\" title=\"Exceptions to deadlines\">some exceptions</a> to these deadlines. </p>\n\n<p>If your tax return or payment is late you must pay a <a href=\"/self-assessment-tax-returns/penalties\" title=\"Penalties\">penalty</a>. </p>\n\n<div class=\"application-notice info-notice\">\n<p>If you’ve missed the paper deadline, <a href=\"/how-to-send-self-assessment-online\" title=\"How to send your tax return online\">send your tax return online</a> instead to avoid a penalty.</p>\n</div>\n\n","alternative_title":""},"tags":[{"title":"Self Assessment","id":"https://www.gov.uk/api/tags/tax%2Fself-assessment.json","web_url":null,"details":{"description":"Includes filing, deadlines, pay and tax records","short_description":null,"type":"section"},"content_with_tag":{"id":"https://www.gov.uk/api/with_tag.json?tag=tax%2Fself-assessment","web_url":"https://www.gov.uk/browse/tax/self-assessment"},"parent":{"title":"Money and tax","id":"https://www.gov.uk/api/tags/tax.json","web_url":null,"details":{"description":"Includes VAT, debt and inheritance tax","short_description":null,"type":"section"},"content_with_tag":{"id":"https://www.gov.uk/api/with_tag.json?tag=tax","web_url":"https://www.gov.uk/browse/tax"},"parent":null}},{"title":"Business Link","id":"https://www.gov.uk/api/tags/businesslink.json","web_url":null,"details":{"description":null,"short_description":null,"type":"legacy_source"},"content_with_tag":{"id":"https://www.gov.uk/api/with_tag.json?tag=businesslink","web_url":"https://www.gov.uk/browse/businesslink"},"parent":null},{"title":"Directgov","id":"https://www.gov.uk/api/tags/directgov.json","web_url":null,"details":{"description":null,"short_description":null,"type":"legacy_source"},"content_with_tag":{"id":"https://www.gov.uk/api/with_tag.json?tag=directgov","web_url":"https://www.gov.uk/browse/directgov"},"parent":null}],"related":[{"id":"https://www.gov.uk/api/difficulties-paying-hmrc.json","web_url":"https://www.gov.uk/difficulties-paying-hmrc","title":"If you can't pay your tax bill on time","format":"guide","updated_at":"2012-10-22T22:46:27+00:00"},{"id":"https://www.gov.uk/api/self-assessment-tax-returns.json","web_url":"https://www.gov.uk/self-assessment-tax-returns","title":"Self Assessment tax returns     ","format":"guide","updated_at":"2012-12-13T16:44:27+00:00"},{"id":"https://www.gov.uk/api/register-for-self-assessment.json","web_url":"https://www.gov.uk/register-for-self-assessment","title":"Register for Self Assessment","format":"answer","updated_at":"2012-12-18T10:01:25+00:00"},{"id":"https://www.gov.uk/api/pay-self-assessment-tax-bill.json","web_url":"https://www.gov.uk/pay-self-assessment-tax-bill","title":"Pay your Self Assessment tax bill","format":"answer","updated_at":"2012-10-29T16:47:25+00:00"}]}