{"alternative_title":"","continuation_link":"","licence_identifier":"9121-7-1","licence_overview":"To net for salmon and sea trout or fish for eels using nets, trawls or traps you need a licence from the [Environment Agency](http://www.environment-agency.gov.uk \"Environment Agency\"){:rel=\"external\"} in England and Wales, or permission from the relevant private land owner in Scotland. \r\n\r\nAn Environment Agency\u00a0consent is required to trap signal crayfish.","licence_short_description":"You need a licence to net for salmon and sea trout or fish for eels using nets, trawls or traps.","overview":"You need a licence to net for salmon and sea trout or fish for eels using nets, trawls or traps","slug":"commercial-inland-fishing-licence","title":"Commercial Inland Fishing Licence","updated_at":"2012-10-02T12:12:26+00:00","will_continue_on":"","type":"licence"}