{"alternative_title":"","body":"$!There are 3 ways to nominate someone to collect your State Pension for you, depending on how you get your payment.$!\r\n\r\n##Direct Payment##\r\n\r\nIf your State Pension is paid to you using Direct Payment and you want to nominate someone to get it for you, you should:\r\n\r\n- contact your bank, building society or other account provider direct\r\n\r\n##Cheque##\r\nIf your State Pension is paid to you using a cheque, and you want someone to cash the cheque for you, you should:\r\n\r\ns1. sign the back of your cheque\r\ns2. get your nominated helper to sign a declaration of what they want to do for you\r\ns3. provide proof of identity at the bank/building society where you want to cash your cheque\r\n\r\n^ A declaration is a written letter stating what a person plans to do. It doesn't have the strength of a legal contract.^\r\n\r\n##Lasting Power of Attorney##\r\n\r\nIf you're no longer able to make decisions on your behalf, and you want to nominate someone to get your State Pension on a more permanent basis then you'll need to set up a [Lasting Power of Attorney](/power-of-attorney \"Lasting Power of Attorney\").","overview":"Find out how to nominate someone to collect your State Pension for you","slug":"nominate-someone-to-collect-state-pension","title":"Nominate someone to collect State Pension","updated_at":"2012-10-02T12:13:32+00:00","type":"answer"}