{"alternative_title":"","body":"$!Your payslip must show your earnings before and after any deductions, explain any deductions and show how your wage is paid.$!\r\n\r\n##Deductions\r\nYour employer must explain any fixed deductions from your wage, eg trade union subscriptions. They must do this either on your payslip, or in a separate written statement. \r\n\r\nYou must be sent this separate statement before your first payslip and your employer must update it annually.\r\n\r\n##When you don't have a right to a payslip\r\nYou don't have the right to a payslip if you're:\r\n\r\n- not an employee, eg contractors, freelancers or 'workers' - [check your employment status](/employment-status \"Employment status\") to see if you're an employee\r\n- in the police service\r\n- a merchant seaman\r\n- master or crew member working in share fishing (paid by a share in the profits or gross earnings of a fishing vessel)\r\n \r\n^ If you have a problem with your payslip you should try sorting it out informally with your employer. ^","overview":"Your wage slip must show any deductions and explain them - find out when you don't have the right to a payslip","slug":"payslips-your-rights","title":"Payslips: your rights ","updated_at":"2012-10-02T12:13:39+00:00","type":"answer"}