{"artefact":[["_response_info",{"status":"ok"}],["title","Register as a paramedic"],["id","https://contentapi.production.alphagov.co.uk/register-paramedic.json"],["web_url","https://www.gov.uk/register-paramedic"],["format","licence"],["details",{"need_id":"1","business_proposition":true,"alternative_title":"","overview":"You need to register with the Health are Care Professions Council (HCPC) to practice as a paramedic","will_continue_on":"the Health and Care Professions Council (HCPC) website","continuation_link":"http://www.hpc-uk.org","licence_identifier":"9193-7-1","licence_short_description":"Register with the Health are Care Professions Council (HCPC) to practice as a paramedic.","licence_overview":"\r\nTo practise as a paramedic, you need to register with the [Health and Care Professions Council (HCPC).](http://www.hpc-uk.org \"Health and Care Professions Council (HCPC)\"){:rel=\"external\"}","updated_at":"2012-10-08T17:08:03+00:00"}],["tags",[{"title":"Licences and licence applications","id":"https://contentapi.production.alphagov.co.uk/tags/business%2Flicences.json","web_url":null,"details":{"description":"Applying for licences from your council for events and businesses","type":"section"},"content_with_tag":{"id":"https://contentapi.production.alphagov.co.uk/with_tag.json?tag=business%2Flicences","web_url":"https://www.gov.uk/browse/business/licences"},"parent":{"title":"Business","id":"https://contentapi.production.alphagov.co.uk/tags/business.json","web_url":null,"details":{"description":"Information about starting up and running a business in the UK, including help if you're self employed or a sole trader.","type":"section"},"content_with_tag":{"id":"https://contentapi.production.alphagov.co.uk/with_tag.json?tag=business","web_url":"https://www.gov.uk/browse/business"},"parent":null}}]],["related",[]]],"parts":null}