{"alternative_title":"Licence to run a business hiring out horses or ponies for riding ","continuation_link":null,"licence_identifier":"696-6-1","licence_overview":"$!If you want to run a riding establishment in England, Scotland or Wales, you'll need to contact your local council to apply for a licence.$!\r\n\r\nA riding establishment is a business that hires out horses or ponies for riding, or a riding school.\r\n\r\nA riding establishment licence needs to be renewed every year. The fee and specific conditions will be set by your council, but there are some common rules and requirements.\r\n\r\n##Requirements\r\n\r\nYou'll need to prove that you have suitable qualifications and experience of horse management, and that your horses are:\r\n\r\n* in good health and physically fit\r\n* suitable to be hired out and used for riding\r\n* provided with adequate food, drink and bedding\r\n* regularly exercised\r\n* safeguarded in an emergency\r\n\r\nYou also need liability insurance that covers you for any injuries that result from people riding your horses.\r\n\r\nYou must keep a register of horses aged 3 years or under that are usually kept on your premises, and make it available for inspection.\r\n\r\n##Restrictions\r\n\r\nYou must be over 18 to apply for a licence. You will not be given a licence if you've committed any animal health or welfare offences, or if you've been banned from:\r\n\r\n* running a riding establishment\r\n* running a pet shop\r\n* keeping animals, including in a boarding kennel or cattery\r\n\r\nYou must not leave anyone under 16 years old in charge of the riding establishment. Any riders under 16 must be supervised, unless you're satisfied that they are competent to ride without supervision.\r\n\r\n##Inspection\r\n\r\nThe council may inspect your premises and horses before giving you a licence, and any time after your licence is granted. If the inspector finds that any of your horses need veterinary attention, you must provide a certificate to show they are fit again before returning them to work.\r\n\r\n%You can be fined up to \u00a35,000 or imprisoned for up to 3 months, or both, if you run a riding establishment without a licence.%","licence_short_description":"Licence to run a business where horses or ponies are hired out for riding or used for riding instruction","overview":"Apply for a riding establishment licence if you want to run a business where horses or ponies are hired out for riding or used for riding instruction in England, Scotland and Wales.","slug":"riding-establishment-licence","title":"Riding establishment licence (England, Scotland and Wales)","updated_at":"2012-10-02T12:14:07+00:00","will_continue_on":null,"type":"licence"}