{"artefact":[["_response_info",{"status":"ok"}],["title","Self Assessment forms and helpsheets"],["id","https://contentapi.production.alphagov.co.uk/self-assessment-forms-and-helpsheets.json"],["web_url","https://www.gov.uk/self-assessment-forms-and-helpsheets"],["format","answer"],["details",{"need_id":"B95","business_proposition":true,"alternative_title":"Download paper Self Assessment tax return forms","overview":"Self Assessment tax return forms and helpsheets for the current tax year and the 3 previous tax years","updated_at":"2012-10-09T18:12:50+00:00","body":"\n<div class=\"summary\">\n<p>Download forms and helpsheets for the past 4 tax years.</p>\n</div>\n\n<div class=\"application-notice help-notice\">\n<p>The deadline for paper tax returns is 31 October. You have until 31 January if you send your return online.</p>\n</div>\n\n<h2>2011 to 2012 tax year</h2>\n\n<p>Download the forms and helpsheets appropriate for your situation:</p>\n\n<ul>\n  <li>\n    <p><a rel=\"external\" href=\"http://search2.hmrc.gov.uk/kb5/hmrc/forms/view.page?record=ZrJXAG2mt_0&amp;formId=2999\" title=\"Self Assessment tax return (SA100) for individuals for the 2011 to 2012 tax year\">Individuals (including the self-employed) tax return (form SA100)</a>  </p>\n  </li>\n  <li>\n    <p><a rel=\"external\" href=\"http://search2.hmrc.gov.uk/kb5/hmrc/forms/view.page?record=LDtfIQn4taY&amp;formId=3109\" title=\"Partnership tax return (SA800) for the 2011 to 2012 tax year\">Partnership tax return (form SA800)</a></p>\n  </li>\n  <li>\n    <p><a rel=\"external\" href=\"http://search2.hmrc.gov.uk/kb5/hmrc/forms/selfassessmentforms.page#2050\" title=\"Trusts and estate tax return (SA900) for the 2011 to 2012 tax year\">Trust and estate tax return (form SA900)</a></p>\n  </li>\n  <li>\n    <p><a rel=\"external\" href=\"http://search2.hmrc.gov.uk/kb5/hmrc/forms/view.page?record=BY1bV6sVDDA&amp;formId=3146\" title=\"Non resident companies tax return (SA700) for the 2011 to 2012 tax year\">Non-resident companies tax return (form SA700)</a></p>\n  </li>\n  <li>\n    <p><a rel=\"external\" href=\"http://search2.hmrc.gov.uk/kb5/hmrc/forms/view.page?record=U2HGJsHggHg&amp;formId=3148\" title=\"Trustees of registered pension schemes tax return (SA970) for the 2011 to 2012 tax year\">Trustees of registered pension schemes tax return (form SA970)</a></p>\n  </li>\n</ul>\n\n<h2>Earlier tax years</h2>\n\n<table>\n  <thead>\n    <tr>\n      <th>Tax return type</th>\n      <th>2010 to 2011 tax year</th>\n      <th>2009 to 2010 tax year</th>\n      <th>2008 to 2009 tax year</th>\n    </tr>\n  </thead>\n  <tbody>\n    <tr>\n      <td>Individuals (including self employed people)</td>\n      <td><a rel=\"external\" href=\"http://search2.hmrc.gov.uk/kb5/hmrc/forms/view.page?record=IL7LRJzxfJ0&amp;formId=6999\" title=\"2010 to 2011 Self Assessment tax return forms and helpsheets for individuals\">SA100</a></td>\n      <td><a rel=\"external\" href=\"http://search2.hmrc.gov.uk/kb5/hmrc/forms/view.page?record=l_agDHNSX7M&amp;formId=5071\" title=\"2009 to 2010 Self Assessment return forms and helpsheets for individuals\">SA100</a></td>\n      <td><a rel=\"external\" href=\"http://search2.hmrc.gov.uk/kb5/hmrc/forms/view.page?record=3GgSUbZFPRc&amp;formId=3720\" title=\"2008 to 2009 Self Assessment tax return forms and helpsheets for individuals\">SA100</a></td>\n    </tr>\n    <tr>\n      <td>Partnership</td>\n      <td><a rel=\"external\" href=\"http://search2.hmrc.gov.uk/kb5/hmrc/forms/view.page?record=nRqQi-Ulk4w&amp;formId=6109\" title=\"2010 to 2011 Partnership tax return forms and helpsheets\">SA800</a></td>\n      <td><a rel=\"external\" href=\"http://search2.hmrc.gov.uk/kb5/hmrc/forms/view.page?record=V7zc9X5-3HI&amp;formId=5113\" title=\"2009 to 2010 Partnership tax return forms and helpsheets\">SA800</a></td>\n      <td><a rel=\"external\" href=\"http://search2.hmrc.gov.uk/kb5/hmrc/forms/view.page?record=4aTOSxxg-TM&amp;formId=3778\" title=\"2008 to 2009 Partnership tax return forms and helpsheets\">SA800</a></td>\n    </tr>\n    <tr>\n      <td>Trust and estate</td>\n      <td><a rel=\"external\" href=\"http://search2.hmrc.gov.uk/kb5/hmrc/forms/view.page?record=WWHRgxFiU1o&amp;formId=6123\" title=\"2010 to 2011 Trust and estate tax return forms and helpsheets\">SA900</a></td>\n      <td><a rel=\"external\" href=\"http://search2.hmrc.gov.uk/kb5/hmrc/forms/view.page?record=iwxZD-_Ukgk&amp;formId=5125\" title=\"2009 to 2010 Trust and estate tax return forms and helpsheets\">SA900</a></td>\n      <td><a rel=\"external\" href=\"http://search2.hmrc.gov.uk/kb5/hmrc/forms/view.page?record=cfnR0w1zhcA&amp;formId=3792\" title=\"2008 to 2009 Trust and estate tax return forms and helpsheets\">SA900</a></td>\n    </tr>\n    <tr>\n      <td>Non-resident companies</td>\n      <td><a rel=\"external\" href=\"http://search2.hmrc.gov.uk/kb5/hmrc/forms/view.page?record=s25VveO1VbE&amp;formId=6146\" title=\"2010 to 2011 non-resident companies liable to income tax returns and helpsheets\">SA700</a></td>\n      <td><a rel=\"external\" href=\"http://search2.hmrc.gov.uk/kb5/hmrc/forms/view.page?record=MnpA-zW5DO4&amp;formId=5111\" title=\"2009 to 2010 non-resident companies liable to income tax returns and helpsheets\">SA700</a></td>\n      <td><a rel=\"external\" href=\"http://search2.hmrc.gov.uk/kb5/hmrc/forms/view.page?record=Dh9P-2-EjDA&amp;formId=3806\" title=\"2008 to 2009 non-resident companies liable to income tax returns and helpsheets\">SA700</a></td>\n    </tr>\n    <tr>\n      <td>Trustees of registered pension schemes</td>\n      <td><a rel=\"external\" href=\"http://search2.hmrc.gov.uk/kb5/hmrc/forms/view.page?record=xcqWYlOgpGE&amp;formId=6148\" title=\"2010 to 2011 tax return forms and helpsheets for trustees of registered pension schemes\">SA970</a></td>\n      <td><a rel=\"external\" href=\"http://search2.hmrc.gov.uk/kb5/hmrc/forms/view.page?record=BiXULnxTMFI&amp;formId=5146\" title=\"2009 to 2010 tax return forms and helpsheets for trustees of registered pension schemes\">SA970</a></td>\n      <td><a rel=\"external\" href=\"http://search2.hmrc.gov.uk/kb5/hmrc/forms/view.page?record=NfDPk5OMD00&amp;formId=3808\" title=\"2008 to 2009 tax return forms and helpsheets for trustees of registered pension schemes\">SA970</a></td>\n    </tr>\n  </tbody>\n</table>\n\n<h2>All Self Assessment forms and helpsheets</h2>\n\n<p>The HM Revenue &amp; Customs website has <a rel=\"external\" href=\"http://search2.hmrc.gov.uk/kb5/hmrc/forms/selfassessmentforms.page\" title=\"Full list of Self Assessment forms and helpsheets\">a full listing</a> of Self Assessment forms and helpsheets, including:</p>\n\n<ul>\n  <li>appeal forms</li>\n  <li>short tax return guidance notes</li>\n  <li>payslip for Self Assessment</li>\n</ul>\n"}],["tags",[{"title":"Self-assessment","id":"https://contentapi.production.alphagov.co.uk/tags/tax%2Fself-assessment.json","web_url":null,"details":{"description":"Includes filing, deadlines, pay and tax records","type":"section"},"content_with_tag":{"id":"https://contentapi.production.alphagov.co.uk/with_tag.json?tag=tax%2Fself-assessment","web_url":"https://www.gov.uk/browse/tax/self-assessment"},"parent":{"title":"Money and tax","id":"https://contentapi.production.alphagov.co.uk/tags/tax.json","web_url":null,"details":{"description":"Includes VAT, debt and inheritance tax","type":"section"},"content_with_tag":{"id":"https://contentapi.production.alphagov.co.uk/with_tag.json?tag=tax","web_url":"https://www.gov.uk/browse/tax"},"parent":null}},{"title":"Business Link","id":"https://contentapi.production.alphagov.co.uk/tags/businesslink.json","web_url":null,"details":{"description":null,"type":"legacy_source"},"content_with_tag":{"id":"https://contentapi.production.alphagov.co.uk/with_tag.json?tag=businesslink","web_url":"https://www.gov.uk/browse/businesslink"},"parent":null},{"title":"Directgov","id":"https://contentapi.production.alphagov.co.uk/tags/directgov.json","web_url":null,"details":{"description":null,"type":"legacy_source"},"content_with_tag":{"id":"https://contentapi.production.alphagov.co.uk/with_tag.json?tag=directgov","web_url":"https://www.gov.uk/browse/directgov"},"parent":null}]],["related",[{"title":"Log in and file your Self Assessment tax return","id":"https://contentapi.production.alphagov.co.uk/file-your-self-assessment-tax-return.json","web_url":"https://www.gov.uk/file-your-self-assessment-tax-return","format":"transaction","details":{"need_id":"1723","business_proposition":true}},{"title":"Self Assessment tax return deadlines 2011 to 2012","id":"https://contentapi.production.alphagov.co.uk/self-assessment-tax-return-deadlines.json","web_url":"https://www.gov.uk/self-assessment-tax-return-deadlines","format":"answer","details":{"need_id":"B100","business_proposition":true}},{"title":"Self Assessment tax returns     ","id":"https://contentapi.production.alphagov.co.uk/self-assessment-tax-returns.json","web_url":"https://www.gov.uk/self-assessment-tax-returns","format":"guide","details":{"need_id":"B126","business_proposition":true}}]]],"parts":null}